dockedup/__init__.py
dockedup/cli.py
dockedup/docker_monitor.py
dockedup/utils.py
dockedup-1.0.1.dist-info/licenses/LICENSE
dockedup-1.0.1.dist-info/METADATA
dockedup-1.0.1.dist-info/WHEEL
dockedup-1.0.1.dist-info/entry_points.txt
dockedup-1.0.1.dist-info/top_level.txt
dockedup-1.0.1.dist-info/RECORD
