Metadata-Version: 2.4
Name: dockedup
Version: 1.0.1
Summary: Your live, beautiful Docker Compose monitor CLI tool.
Author-email: Anil Raj Rimal <anilrajrimal@gmail.com>
License: MIT
Project-URL: Homepage, https://github.com/anilrajrimal1/dockedup
Project-URL: Repository, https://github.com/anilrajrimal1/dockedup
Project-URL: Documentation, https://github.com/anilrajrimal1/dockedup/wiki
Project-URL: Bug Reports, https://github.com/anilrajrimal1/dockedup/issues
Keywords: docker,compose,monitor,htop,cli,containers,devops
Classifier: Development Status :: 4 - Beta
Classifier: Environment :: Console
Classifier: Intended Audience :: Developers
Classifier: Intended Audience :: System Administrators
Classifier: License :: OSI Approved :: MIT License
Classifier: Operating System :: OS Independent
Classifier: Programming Language :: Python :: 3
Classifier: Programming Language :: Python :: 3.8
Classifier: Programming Language :: Python :: 3.9
Classifier: Programming Language :: Python :: 3.10
Classifier: Programming Language :: Python :: 3.11
Classifier: Programming Language :: Python :: 3.12
Classifier: Topic :: System :: Monitoring
Classifier: Topic :: System :: Systems Administration
Classifier: Topic :: Utilities
Requires-Python: >=3.10
License-File: LICENSE
Requires-Dist: typer>=0.9.0
Requires-Dist: rich>=13.0.0
Requires-Dist: docker>=6.0.0
Requires-Dist: readchar>=4.0.0
Requires-Dist: typing-extensions>=4.0.0
Provides-Extra: dev
Requires-Dist: pytest>=7.0.0; extra == "dev"
Requires-Dist: pytest-cov>=4.0.0; extra == "dev"
Requires-Dist: black>=23.0.0; extra == "dev"
Requires-Dist: mypy>=1.0.0; extra == "dev"
Requires-Dist: pre-commit>=3.0.0; extra == "dev"
Requires-Dist: build>=0.10.0; extra == "dev"
Requires-Dist: twine>=4.0.0; extra == "dev"
Dynamic: license-file
